{"stat.useItem.6":128,"stat.useItem.18":3,"stat.useItem.17":2,"stat.fallOneCm":13209,"achievement.openInventory":52,"stat.jump":159,"achievement.exploreAllBiomes":{"value":0,"progress":["Forest","Extreme Hills","River"]},"stat.mineBlock.31":1,"stat.damageTaken":1100,"stat.deaths":1,"stat.mineBlock.1":39,"stat.drop":73,"stat.flyOneCm":47074,"stat.mineBlock.3":9,"stat.useItem.278":46,"stat.mineBlock.18":6,"stat.mineBlock.17":39,"stat.mineBlock.6":10,"stat.diveOneCm":181,"stat.walkOneCm":88954,"stat.swimOneCm":609,"stat.useItem.47":17,"stat.mineBlock.47":2,"stat.useItem.116":1,"stat.mineBlock.106":2,"stat.playOneMinute":19296,"achievement.mineWood":448}